safeshield-1.6.11.dist-info/licenses/LICENSE
validator/__init__.py
validator/exceptions.py
validator/factory.py
validator/core/__init__.py
validator/core/validator.py
validator/database/__init__.py
validator/database/detector.py
validator/database/manager.py
validator/rules/__init__.py
validator/rules/array.py
validator/rules/base.py
validator/rules/basic.py
validator/rules/boolean.py
validator/rules/comparison.py
validator/rules/date.py
validator/rules/files.py
validator/rules/format.py
validator/rules/numeric.py
validator/rules/string.py
validator/rules/utilities.py
validator/services/__init__.py
validator/services/rule_conflict.py
validator/services/rule_error_handler.py
validator/services/rule_preparer.py
validator/utils/__init__.py
validator/utils/string.py
safeshield-1.6.11.dist-info/METADATA
safeshield-1.6.11.dist-info/WHEEL
safeshield-1.6.11.dist-info/top_level.txt
safeshield-1.6.11.dist-info/RECORD
