Metadata-Version: 2.4
Name: safeshield
Version: 1.6.11
Summary: Library for Help Validation Control
Home-page: https://github.com/WunsunTarniho/py-guard
Author: Wunsun Tarniho
Author-email: wunsun58@gmail.com
Project-URL: Bug Tracker, https://github.com/WunsunTarniho/py-guard/issues
Classifier: Intended Audience :: Developers
Classifier: Programming Language :: Python :: 3.10
Classifier: Programming Language :: Python :: 3.11
Classifier: License :: OSI Approved :: MIT License
Classifier: Operating System :: OS Independent
Classifier: Topic :: Software Development :: Libraries :: Python Modules
Classifier: Topic :: Security
Requires-Python: >=3.10
License-File: LICENSE
Requires-Dist: mysql-connector-python==8.0.33
Requires-Dist: Pillow==11.2.1
Requires-Dist: psycopg2-binary==2.9.9
Requires-Dist: python-dotenv==1.1.1
Requires-Dist: python_dateutil==2.9.0.post0
Requires-Dist: SQLAlchemy==2.0.41
Requires-Dist: Werkzeug==1.0.1
Requires-Dist: dnspython==2.4.2
Requires-Dist: idna==3.6
Dynamic: author
Dynamic: author-email
Dynamic: classifier
Dynamic: description
Dynamic: description-content-type
Dynamic: home-page
Dynamic: license-file
Dynamic: project-url
Dynamic: requires-dist
Dynamic: requires-python
Dynamic: summary
